main.py
lightseeq-98.7.dist-info/METADATA
lightseeq-98.7.dist-info/WHEEL
lightseeq-98.7.dist-info/top_level.txt
lightseeq-98.7.dist-info/RECORD
